nameko_worker_postmortem.py
nameko_worker_postmortem-1.0.0.dist-info/METADATA
nameko_worker_postmortem-1.0.0.dist-info/RECORD
nameko_worker_postmortem-1.0.0.dist-info/WHEEL
nameko_worker_postmortem-1.0.0.dist-info/entry_points.txt
nameko_worker_postmortem-1.0.0.dist-info/top_level.txt
nameko_worker_postmortem-1.0.0.dist-info/zip-safe
