Metadata-Version: 2.1
Name: nameko-worker-postmortem
Version: 1.0.0
Summary: Drop into PDB post mortem on Nameko worker exceptions
Home-page: http://github.com/mattbennett/nameko-worker-postmortem
Author: mattbennett
License: Apache License, Version 2.0
Platform: UNKNOWN
Classifier: Programming Language :: Python
Classifier: Operating System :: MacOS :: MacOS X
Classifier: Operating System :: POSIX
Classifier: Programming Language :: Python :: 3
Classifier: Topic :: Internet
Classifier: Topic :: Software Development :: Libraries :: Python Modules
Classifier: Intended Audience :: Developers
Provides-Extra: dev
Requires-Dist: nameko
Requires-Dist: pytest
Provides-Extra: dev
Requires-Dist: coverage (==4.4.1); extra == 'dev'
